README.md
setup.py
trainbench/ParametersLoader.py
trainbench/__init__.py
trainbench/__main__.py
trainbench/trainer.py
trainbench.egg-info/PKG-INFO
trainbench.egg-info/SOURCES.txt
trainbench.egg-info/dependency_links.txt
trainbench.egg-info/entry_points.txt
trainbench.egg-info/top_level.txt