Metadata-Version: 2.1
Name: trainbench
Version: 0.0.2
Summary: A tool for training deep learning cross validation training.
Home-page: https://github.com/danfergo/trainbench
Author: danfergo
Author-email: e-windlidar@googlegroups.com
License: UNKNOWN
Keywords: deep,learning,cross,validation
Platform: UNKNOWN
